[
    {
        "_id": "123456789",
        "name": "דוד מוזס",
        "type": "admin",
        "joined_date": "01/01/2001",
        "tools": [

        ]
    } , {
        "_id": "315568991",
        "name": "יוחאי רשף",
        "type": "team manager",
        "joined_date": "07/07/1951",
        "tools": [

        ]
    } , {
        "_id": "504425136",
        "name": "משתאווה ברנבנק",
        "type": "volunteer",
        "joined_date": "02/12/1987",
        "tools": [

        ]
    } , {
        "_id": "138548975",
        "name": "פנחס נשכותי",
        "type": "volunteer",
        "joined_date": "15/05/2004",
        "tools": [

        ]
    } , {
        "_id": "393116710",
        "name": "אלכס דפקותי",
        "type": "volunteer",
        "joined_date": "10/09/2011",
        "tools": [

        ]
    } , {
        "_id": "868876951",
        "name": "מליין סופרי",
        "type": "volunteer",
        "joined_date": "10/09/2013",
        "tools": [

        ]
    }
]
